frequenz/repo/py.typed
frequenz/repo/config/__init__.py
frequenz/repo/config/_core.py
frequenz/repo/config/github.py
frequenz/repo/config/protobuf.py
frequenz/repo/config/version.py
frequenz/repo/config/cli/__init__.py
frequenz/repo/config/cli/version/__init__.py
frequenz/repo/config/cli/version/mike/__init__.py
frequenz/repo/config/cli/version/mike/info.py
frequenz/repo/config/cli/version/mike/sort.py
frequenz/repo/config/mkdocs/__init__.py
frequenz/repo/config/mkdocs/annotations.py
frequenz/repo/config/mkdocs/api_pages.py
frequenz/repo/config/mkdocs/mike.py
frequenz/repo/config/mkdocs/mkdocstrings_macros.py
frequenz/repo/config/nox/__init__.py
frequenz/repo/config/nox/config.py
frequenz/repo/config/nox/default.py
frequenz/repo/config/nox/session.py
frequenz/repo/config/nox/util.py
frequenz/repo/config/pytest/__init__.py
frequenz/repo/config/pytest/examples.py
frequenz/repo/config/setuptools/__init__.py
frequenz/repo/config/setuptools/grpc_tools.py
frequenz_repo_config-0.14.0.dist-info/licenses/LICENSE
frequenz_repo_config-0.14.0.dist-info/METADATA
frequenz_repo_config-0.14.0.dist-info/WHEEL
frequenz_repo_config-0.14.0.dist-info/entry_points.txt
frequenz_repo_config-0.14.0.dist-info/top_level.txt
frequenz_repo_config-0.14.0.dist-info/RECORD
